{
  "wallpapers": [
    {
            "name": "01",
            "author": "unknown",
            "url": "https://raw.githubusercontent.com/vk41/elevenui/master/20170922_003615.png"
        },
        {
            "name": "02",
            "author": "unknown",
            "url": "https://raw.githubusercontent.com/vk41/elevenui/master/Flower_HELLEBORUS-iOS-11-GM-iPad-wallpapers.jpg"
        },
        {
            "name": "03",
            "author": "unknown",
            "url": "https://raw.githubusercontent.com/vk41/elevenui/master/gradient-26052-26737-hd-wallpapers.jpg.png"
        },
    {
            "name": "04",
            "author": "unknown",
            "url": "https://raw.githubusercontent.com/vk41/elevenui/master/red-linear-purple-gradient-1920x1080-c2-fa8072-9932cc-a-255-f-14.png"
        },
        {
            "name": "05",
            "author": "unknown",
            "url": "https://raw.githubusercontent.com/vk41/elevenui/master/samsung_galaxy_s8_qhd_droidviews_09.jpg"
        },
        {
            "name": "06",
            "author": "unknown",
            "url": "https://raw.githubusercontent.com/vk41/elevenui/master/ssv_thuyican_3.png"
        },
    {
            "name": "07",
            "author": "unknown",
            "url": "https://raw.githubusercontent.com/vk41/elevenui/master/ssv_thuyican_4.png"
        }
  ]
}
